<?xml version="1.0" encoding="utf-8"?>
<odoo>
	<record id="hr_expense_view_expenses_analysis_tree_inherit" model="ir.ui.view">
        <field name="name">hr.expense.tree.inherit</field>
        <field name="model">hr.expense</field>
        <field name="inherit_id" ref="hr_expense.hr_expense_view_expenses_analysis_tree"/>
        <field name="arch" type="xml">
			<xpath expr="//field[@name='name']" position="before">				                
                <field name="number"/>	                
			</xpath>                
        </field>
    </record>

    <record id="hr_expense_view_form_inherit" model="ir.ui.view">
        <field name="name">hr.expense.form.inherit</field>
        <field name="model">hr.expense</field>
        <field name="inherit_id" ref="hr_expense.hr_expense_view_form"/>
        <field name="arch" type="xml">
			<xpath expr="//div[@class='oe_title']" position="replace">				
                <h1>
                    <field name="number" readonly="1"/>
                </h1>					
                <label for="name"/>
                <field name="name"/>	                
			</xpath>                
        </field>
    </record>
    
    <record id="view_hr_expense_sheet_tree_inherit" model="ir.ui.view">
        <field name="name">hr.expense.sheet.tree.inherit</field>
        <field name="model">hr.expense.sheet</field>
        <field name="inherit_id" ref="hr_expense.view_hr_expense_sheet_tree"/>
        <field name="arch" type="xml">
			<xpath expr="//field[@name='name']" position="before">				                
                <field name="number"/>	                
			</xpath>                
        </field>
    </record>
    
    <record id="view_hr_expense_sheet_form_inherit" model="ir.ui.view">
        <field name="name">hr.expense.sheet.form.inherit</field>
        <field name="model">hr.expense.sheet</field>
        <field name="inherit_id" ref="hr_expense.view_hr_expense_sheet_form"/>
        <field name="arch" type="xml">
			<xpath expr="//field[@name='bank_journal_id']" position="replace">
				<field name="is_cash_advance" invisible="1"/>
				<field name="cash_advance_id" domain="[('state','=','done'),('expense_report_id','=',False)]" options="{'no_open': True, 'no_create': True}" attrs="{'invisible': [('is_cash_advance','=',False)], 'required': [('is_cash_advance','=',True)]}"/>
				<field name="bank_journal_id" domain="[('type', 'in', ['cash', 'bank'])]" attrs="{'invisible': [('is_cash_advance','=',False)]}"/>
				<field name="bank_journal_id" domain="[('is_report_cash_advance', '=', True)]" attrs="{'invisible': [('is_cash_advance','=',True)]}"/>				               				
			</xpath>
			<xpath expr="//field[@name='accounting_date']" position="after">
				<field name="number" readonly="1"/>
			</xpath>			
			<xpath expr="//div[@name='button_box']" position="inside">
				<button name="action_get_difference_view" class="oe_stat_button" icon="fa-money" type="object" attrs="{'invisible': [('different_amount', '=', 0)]}">
				    <field name="different_amount" widget="statinfo" string="Selisih"/>
				</button>			                                   
          	</xpath> 			            
        </field>
    </record>
    
    <record id="hr_expense_sheet_view_search_inherit" model="ir.ui.view">
		<field name="name">hr.expense.sheet.view.search.inherit</field>
		<field name="model">hr.expense.sheet</field>
		<field name="inherit_id" ref="hr_expense.hr_expense_sheet_view_search"/>
		<field name="arch" type="xml">
			<xpath expr="//filter[@name='activities_overdue']" position="after">
				<filter domain="[('is_cash_advance', '=', True)]" string="Cash Advance" name="cash_advance" groups="hr_expense.group_hr_expense_user,hr_expense.group_hr_expense_manager"/>
			</xpath>	        
		</field>
	</record>
	
	<record id="action_hr_expense_sheet_ca" model="ir.actions.act_window">
        <field name="name">Pertanggung Jawaban (PJW)</field>
        <field name="res_model">hr.expense.sheet</field>
        <field name="view_mode">tree,kanban,form,pivot,graph,activity</field>
        <field name="search_view_id" ref="hr_expense.hr_expense_sheet_view_search"/>
        <field name="domain">[('state', '!=', 'cancel'),('is_cash_advance', '=', true)]</field>
        <field name="context">{'search_default_is_cash_advance': 1, 'default_is_cash_advance': 1}</field>
        <field name="help" type="html">
          <p class="o_view_nocontent_smiling_face">
            No expense report found. Let's create one!
          </p><p>
            Once you have created your expense, submit it to your manager who will validate it.
          </p>
        </field>
    </record>
    
    <menuitem id="hr_expense.menu_hr_expense_my_expenses" name="Payment Request" sequence="1" parent="hr_expense.menu_hr_expense_root" groups="base.group_user"/>
    
    <menuitem id="menu_hr_expense_my_ca" name="Cash Advance" sequence="1" parent="hr_expense.menu_hr_expense_root" groups="base.group_user"/>
   	<menuitem id="menu_cash_advance" sequence="1" parent="menu_hr_expense_my_ca" action="action_cash_advance_views" name="Cash Advance"/>
    <menuitem id="menu_ca_report" sequence="2" parent="menu_hr_expense_my_ca" action="action_hr_expense_sheet_ca" name="Pertanggung Jawaban (PJW)"/>
</odoo>
